WinDll/__init__.py
WinDll/kernel32.py
WinDll/user32.py
windll_python-0.1.0.post1.dist-info/METADATA
windll_python-0.1.0.post1.dist-info/WHEEL
windll_python-0.1.0.post1.dist-info/top_level.txt
windll_python-0.1.0.post1.dist-info/RECORD
