Metadata-Version: 2.4
Name: windll-python
Version: 0.1.0.post1
Summary: Easy way to use windows dlls with python.
Home-page: https://github.com/CSDC-K/WinDll
Author: CSDC-K VV
Author-email: mark.mark34234@gmail.com
Classifier: Programming Language :: Python :: 3
Classifier: Operating System :: OS Independent
Requires-Python: >=3.10
Dynamic: author
Dynamic: author-email
Dynamic: classifier
Dynamic: description
Dynamic: description-content-type
Dynamic: home-page
Dynamic: requires-python
Dynamic: summary
